dsadd/__init__.py
dsadd/checks.py
dsadd/decorators.py
dsadd-0.0.2.dist-info/DESCRIPTION.rst
dsadd-0.0.2.dist-info/METADATA
dsadd-0.0.2.dist-info/metadata.json
dsadd-0.0.2.dist-info/RECORD
dsadd-0.0.2.dist-info/top_level.txt
dsadd-0.0.2.dist-info/WHEEL
